corear/__init__.py
corear/core/core.bf
corear/main.py
corear/master.bf
corear/src/RUNME.bf
corear-0.1.0.dist-info/METADATA
corear-0.1.0.dist-info/WHEEL
corear-0.1.0.dist-info/RECORD
