Metadata-Version: 2.1
Name: corear
Version: 0.1.0
Summary: Runner tool for HAI CONVERSE Agents
Author: Jaseunda
Author-email: me@jaseunda.com
Requires-Python: >=3.10,<4.0
Classifier: Programming Language :: Python :: 3
Classifier: Programming Language :: Python :: 3.10
Classifier: Programming Language :: Python :: 3.11
